datasafe/__init__.py
datasafe/checksum.py
datasafe/client.py
datasafe/configuration.py
datasafe/exceptions.py
datasafe/loi.py
datasafe/manifest.py
datasafe/server.py
datasafe/utils.py
labinform_datasafe-0.1.0b1.dist-info/LICENSE
labinform_datasafe-0.1.0b1.dist-info/METADATA
labinform_datasafe-0.1.0b1.dist-info/WHEEL
labinform_datasafe-0.1.0b1.dist-info/entry_points.txt
labinform_datasafe-0.1.0b1.dist-info/top_level.txt
labinform_datasafe-0.1.0b1.dist-info/RECORD
