Metadata-Version: 2.1
Name: labinform-datasafe
Version: 0.1.0b1
Summary: A local repository for warm research data
Home-page: https://www.labinform.de/
Author: Mirjam Schröder, Till Biskup
Author-email: till@till-biskup.de
Project-URL: Documentation, https://datasafe.docs.labinform.de/
Project-URL: Source, https://github.com/tillbiskup/labinform-datasafe
Keywords: Reproducible research,data storage,repository,warm research data,checksums
Classifier: Programming Language :: Python :: 3
Classifier: Programming Language :: Python :: 3.9
Classifier: Programming Language :: Python :: 3.10
Classifier: Programming Language :: Python :: 3.11
Classifier: Programming Language :: Python :: 3.12
Classifier: License :: OSI Approved :: BSD License
Classifier: Operating System :: OS Independent
Classifier: Intended Audience :: Science/Research
Classifier: Development Status :: 4 - Beta
Classifier: Topic :: Scientific/Engineering
Requires-Python: >=3.7
License-File: LICENSE
Requires-Dist: flask
Requires-Dist: oyaml
Provides-Extra: deployment
Requires-Dist: build ; extra == 'deployment'
Requires-Dist: twine ; extra == 'deployment'
Provides-Extra: dev
Requires-Dist: prospector ; extra == 'dev'
Requires-Dist: bandit ; extra == 'dev'
Requires-Dist: pyroma ; extra == 'dev'
Requires-Dist: black ; extra == 'dev'
Requires-Dist: flask-unittest ; extra == 'dev'
Provides-Extra: docs
Requires-Dist: sphinx ; extra == 'docs'
Requires-Dist: sphinx-rtd-theme ; extra == 'docs'
